aishu/__init__.py
aishu/anyrobot.py
aishu/setting.py
aishu/datafaker/__init__.py
aishu/datafaker/anyrobot/__init__.py
aishu/datafaker/anyrobot/getSqlVaule.py
aishu/datafaker/anyrobot/sqlMapping.py
aishu/datafaker/profession/__init__.py
aishu/datafaker/profession/getFiledValue.py
aishu/datafaker/profession/entity/AssociationMapping.py
aishu/datafaker/profession/entity/CreateTestPort.py
aishu/datafaker/profession/entity/DataManage.py
aishu/datafaker/profession/entity/ParaDateFiled.py
aishu/datafaker/profession/entity/RetrievesAssociated.py
aishu/datafaker/profession/entity/__init__.py
aishu/datafaker/profession/entity/agent.py
aishu/datafaker/profession/entity/arPort.py
aishu/datafaker/profession/entity/databaseInfo.py
aishu/datafaker/profession/entity/date.py
aishu/datafaker/profession/entity/id.py
aishu/datafaker/profession/entity/index.py
aishu/datafaker/profession/entity/ip.py
aishu/datafaker/profession/entity/kai.py
aishu/datafaker/profession/entity/ml.py
aishu/datafaker/profession/entity/name.py
aishu/datafaker/profession/entity/objectManager.py
aishu/datafaker/profession/entity/port.py
aishu/datafaker/profession/entity/switch.py
aishu/datafaker/profession/entity/testMail.py
aishu/datafaker/profession/entity/timestamp.py
aishu/datafaker/profession/entity/zx.py
aishu/public/__init__.py
aishu/public/db_select.py
aishu/public/mysql_pool.py
aishu/public/operationJson.py
aishu/public/urlJoin.py
AnyRobot-1.5.4.dist-info/LICENSE
AnyRobot-1.5.4.dist-info/METADATA
AnyRobot-1.5.4.dist-info/WHEEL
AnyRobot-1.5.4.dist-info/top_level.txt
AnyRobot-1.5.4.dist-info/RECORD
