Metadata-Version: 2.1
Name: AnyRobot
Version: 1.5.4
Summary: This is a data service module that solves test data problems.
Home-page: https://mp.weixin.qq.com/s/v6FS96ifCoMvp_rwrhzhKw
Author: Evan.hu
Author-email: 1056212287@qq.com
License: BSD License
Platform: all
Classifier: Intended Audience :: Developers
Classifier: Operating System :: OS Independent
Classifier: Natural Language :: Chinese (Simplified)
Classifier: Programming Language :: Python :: 3.5
Classifier: Programming Language :: Python :: 3.6
Classifier: Programming Language :: Python :: 3.7
Classifier: Programming Language :: Python :: 3.8
Classifier: Topic :: Software Development :: Libraries
